bag_nl/cli.py
bag_nl/geo.py
bag_nl/importer.py
bag_nl/tile.py
bag_nl/sqlite/lig.sql
bag_nl/sqlite/num.sql
bag_nl/sqlite/opr.sql
bag_nl/sqlite/pnd.sql
bag_nl/sqlite/sta.sql
bag_nl/sqlite/text.sql
bag_nl/sqlite/vbo.sql
bag_nl/sqlite/vbo_pnd.sql
bag_nl/sqlite/vbo_purpose.sql
bag_nl/sqlite/wpl.sql
bag_nl/sqlite/wpl_gem.sql
bag_nl-0.1.0.dist-info/METADATA
bag_nl-0.1.0.dist-info/WHEEL
bag_nl-0.1.0.dist-info/entry_points.txt
bag_nl-0.1.0.dist-info/RECORD
