Metadata-Version: 2.4
Name: bag-nl
Version: 0.1.0
Summary: BAG tools
Author-email: Hans Gremmen <hans@leptonix.net>
License: MIT
Requires-Python: >=3.12
Requires-Dist: dpath>=2.1.6
Requires-Dist: inceptum>=0.5.0
Requires-Dist: tqdm>=4.66.0
Provides-Extra: test
Requires-Dist: pytest>=8; extra == 'test'
